clusterops/__init__.py
clusterops/cpu_exec_decorator.py
clusterops/execute_callables_parallel.py
clusterops/main.py
clusterops/profiling_exec.py
clusterops-0.2.1.dist-info/LICENSE
clusterops-0.2.1.dist-info/METADATA
clusterops-0.2.1.dist-info/WHEEL
clusterops-0.2.1.dist-info/RECORD
